{
  "year": 1391,
  "course": "ce",
  "total_parsed": 99,
  "questions": [
    {
      "id": 1,
      "answer": 1
    },
    {
      "id": 2,
      "answer": 1
    },
    {
      "id": 3,
      "answer": 1
    },
    {
      "id": 4,
      "answer": 1
    },
    {
      "id": 5,
      "answer": 1
    },
    {
      "id": 6,
      "answer": 1
    },
    {
      "id": 7,
      "answer": 1
    },
    {
      "id": 8,
      "answer": 1
    },
    {
      "id": 9,
      "answer": 1
    },
    {
      "id": 10,
      "answer": 1
    },
    {
      "id": 11,
      "answer": 1
    },
    {
      "id": 12,
      "answer": 1
    },
    {
      "id": 13,
      "answer": 1
    },
    {
      "id": 14,
      "answer": 1
    },
    {
      "id": 15,
      "answer": 1
    },
    {
      "id": 16,
      "answer": 1
    },
    {
      "id": 17,
      "answer": 1
    },
    {
      "id": 18,
      "answer": 1
    },
    {
      "id": 19,
      "answer": 1
    },
    {
      "id": 20,
      "answer": 1
    },
    {
      "id": 21,
      "answer": 1
    },
    {
      "id": 22,
      "answer": 1
    },
    {
      "id": 23,
      "answer": 1
    },
    {
      "id": 24,
      "answer": 1
    },
    {
      "id": 25,
      "answer": 1
    },
    {
      "id": 26,
      "answer": 1
    },
    {
      "id": 27,
      "answer": 1
    },
    {
      "id": 28,
      "answer": 1
    },
    {
      "id": 29,
      "answer": 1
    },
    {
      "id": 30,
      "answer": 1
    },
    {
      "id": 31,
      "answer": 1
    },
    {
      "id": 32,
      "answer": 1
    },
    {
      "id": 33,
      "answer": 1
    },
    {
      "id": 34,
      "answer": 1
    },
    {
      "id": 35,
      "answer": 1
    },
    {
      "id": 36,
      "answer": 1
    },
    {
      "id": 37,
      "answer": 1
    },
    {
      "id": 38,
      "answer": 1
    },
    {
      "id": 39,
      "answer": 1
    },
    {
      "id": 40,
      "answer": 1
    },
    {
      "id": 41,
      "answer": 1
    },
    {
      "id": 42,
      "answer": 1
    },
    {
      "id": 43,
      "answer": 1
    },
    {
      "id": 44,
      "answer": 1
    },
    {
      "id": 45,
      "answer": 1
    },
    {
      "id": 46,
      "answer": 1
    },
    {
      "id": 47,
      "answer": 1
    },
    {
      "id": 48,
      "answer": 1
    },
    {
      "id": 49,
      "answer": 1
    },
    {
      "id": 50,
      "answer": 1
    },
    {
      "id": 51,
      "answer": 1
    },
    {
      "id": 52,
      "answer": 1
    },
    {
      "id": 53,
      "answer": 1
    },
    {
      "id": 54,
      "answer": 1
    },
    {
      "id": 55,
      "answer": 1
    },
    {
      "id": 56,
      "answer": 1
    },
    {
      "id": 57,
      "answer": 1
    },
    {
      "id": 58,
      "answer": 1
    },
    {
      "id": 59,
      "answer": 1
    },
    {
      "id": 60,
      "answer": 1
    },
    {
      "id": 61,
      "answer": 1
    },
    {
      "id": 62,
      "answer": 1
    },
    {
      "id": 63,
      "answer": 1
    },
    {
      "id": 64,
      "answer": 1
    },
    {
      "id": 65,
      "answer": 1
    },
    {
      "id": 66,
      "answer": 1
    },
    {
      "id": 67,
      "answer": 1
    },
    {
      "id": 68,
      "answer": 1
    },
    {
      "id": 69,
      "answer": 1
    },
    {
      "id": 70,
      "answer": 1
    },
    {
      "id": 71,
      "answer": 1
    },
    {
      "id": 72,
      "answer": 1
    },
    {
      "id": 73,
      "answer": 1
    },
    {
      "id": 74,
      "answer": 1
    },
    {
      "id": 75,
      "answer": 1
    },
    {
      "id": 76,
      "answer": 1
    },
    {
      "id": 77,
      "answer": 1
    },
    {
      "id": 78,
      "answer": 1
    },
    {
      "id": 79,
      "answer": 1
    },
    {
      "id": 80,
      "answer": 1
    },
    {
      "id": 81,
      "answer": 1
    },
    {
      "id": 82,
      "answer": 1
    },
    {
      "id": 83,
      "answer": 1
    },
    {
      "id": 84,
      "answer": 1
    },
    {
      "id": 85,
      "answer": 1
    },
    {
      "id": 86,
      "answer": 1
    },
    {
      "id": 87,
      "answer": 1
    },
    {
      "id": 88,
      "answer": 1
    },
    {
      "id": 89,
      "answer": 1
    },
    {
      "id": 90,
      "answer": 1
    },
    {
      "id": 91,
      "answer": 1
    },
    {
      "id": 92,
      "answer": 1
    },
    {
      "id": 93,
      "answer": 1
    },
    {
      "id": 94,
      "answer": 1
    },
    {
      "id": 95,
      "answer": 1
    },
    {
      "id": 96,
      "answer": 1
    },
    {
      "id": 97,
      "answer": 1
    },
    {
      "id": 98,
      "answer": 1
    },
    {
      "id": 99,
      "answer": 1
    }
  ],
  "page_reports": [
    {
      "page": 1,
      "rows": 56,
      "entries": 119,
      "sample_rows": [
        [
          "1",
          "A",
          "7721"
        ],
        [
          "1",
          "1",
          "62",
          "3",
          "15",
          "2",
          "67",
          "3"
        ],
        [
          "2",
          "4",
          "72",
          "1",
          "25",
          "3",
          "77",
          "2"
        ],
        [
          "3",
          "2",
          "82",
          "4",
          "35",
          "4",
          "87",
          "2"
        ],
        [
          "4",
          "3",
          "92",
          "2",
          "45",
          "3",
          "97",
          "2"
        ]
      ]
    },
    {
      "page": 2,
      "rows": 57,
      "entries": 103,
      "sample_rows": [
        [
          "122",
          "152",
          "182",
          "113"
        ],
        [
          "222",
          "252",
          "282",
          "213"
        ],
        [
          "322",
          "352",
          "382",
          "313"
        ],
        [
          "422",
          "452",
          "482",
          "413"
        ],
        [
          "522",
          "552",
          "582",
          "513"
        ]
      ]
    },
    {
      "page": 3,
      "rows": 60,
      "entries": 214,
      "sample_rows": [
        [
          "201",
          "4",
          "231",
          "261",
          "291"
        ],
        [
          "301",
          "331",
          "361",
          "391"
        ],
        [
          "401",
          "2",
          "431",
          "461",
          "491"
        ],
        [
          "501",
          "1",
          "531",
          "561",
          "591"
        ],
        [
          "601",
          "1",
          "631",
          "661",
          "691"
        ]
      ]
    },
    {
      "page": 4,
      "rows": 64,
      "entries": 155,
      "sample_rows": [
        [
          "1",
          "1",
          "62",
          "3",
          "15",
          "2",
          "67",
          "3"
        ],
        [
          "2",
          "2",
          "72",
          "1",
          "25",
          "3",
          "77",
          "4"
        ],
        [
          "3",
          "4",
          "82",
          "2",
          "35",
          "4",
          "87",
          "4"
        ],
        [
          "4",
          "3",
          "92",
          "4",
          "45",
          "3",
          "97",
          "4"
        ],
        [
          "5",
          "4",
          "03",
          "1",
          "55",
          "3",
          "08",
          "2"
        ]
      ]
    },
    {
      "page": 5,
      "rows": 60,
      "entries": 110,
      "sample_rows": [
        [
          "032",
          "062",
          "092",
          "023"
        ],
        [
          "132",
          "162",
          "192"
        ],
        [
          "232",
          "262",
          "292"
        ],
        [
          "332",
          "362",
          "392"
        ],
        [
          "432",
          "462",
          "492"
        ]
      ]
    },
    {
      "page": 6,
      "rows": 48,
      "entries": 171,
      "sample_rows": [
        [
          "311",
          "2",
          "341",
          "371",
          "302"
        ],
        [
          "411",
          "4",
          "441",
          "471",
          "402"
        ],
        [
          "511",
          "2",
          "541",
          "571",
          "502"
        ],
        [
          "611",
          "2",
          "641",
          "671",
          "602"
        ],
        [
          "711",
          "2",
          "741",
          "771",
          "702"
        ]
      ]
    }
  ]
}